tcli_bar.py
tcli_bar-3.0.dist-info/METADATA
tcli_bar-3.0.dist-info/WHEEL
tcli_bar-3.0.dist-info/top_level.txt
tcli_bar-3.0.dist-info/RECORD
