Metadata-Version: 2.1
Name: tcli-bar
Version: 3.0
Summary: Create a CLI progress bar for your python project
Home-page: UNKNOWN
Author: SiXFeet
Author-email: chukunekunwanwene@gmail.com
License: UNKNOWN
Keywords: cli loading bar
Platform: UNKNOWN
Classifier: Programming Language :: Python :: 3
Classifier: License :: OSI Approved :: MIT License
Classifier: Operating System :: OS Independent
Requires-Dist: colorama
